pydaisi/__init__.py
pydaisi/__version__.py
pydaisi/pydaisi.py
pydaisi/shared_data.py
pydaisi/worker_client.py
pydaisi-0.3.3.0.dist-info/LICENSE
pydaisi-0.3.3.0.dist-info/METADATA
pydaisi-0.3.3.0.dist-info/WHEEL
pydaisi-0.3.3.0.dist-info/top_level.txt
pydaisi-0.3.3.0.dist-info/RECORD
