Metadata-Version: 2.1
Name: pydaisi
Version: 0.3.3.0
Summary: A Python Client Interface for the Daisi Platform
Home-page: https://github.com/BelmontTechnology/PyDaisi
Author: Daisi Technology, Inc.
Author-email: eng@daisi.io
License: Apache License 2.0
Project-URL: Documentation, https://doc.daisi.io/
Project-URL: Source, https://github.com/daisi-io/PyDaisi
Keywords: Daisi SDK
Requires-Python: >=3.8
License-File: LICENSE
Requires-Dist: requests
Requires-Dist: httpx
Requires-Dist: python-dotenv
Requires-Dist: dill
Requires-Dist: rich
Requires-Dist: requests-toolbelt
Requires-Dist: trio
Requires-Dist: tqdm
